v440/__init__.py
v440/_core/Local.py
v440/_core/Parser.py
v440/_core/Pattern.py
v440/_core/Pre.py
v440/_core/Release.py
v440/_core/Version.py
v440/_core/__init__.py
v440/_core/utils.py
v440/tests/__init__.py
v440/tests/test_version.py
v440-1.1.1.dist-info/LICENSE.txt
v440-1.1.1.dist-info/METADATA
v440-1.1.1.dist-info/WHEEL
v440-1.1.1.dist-info/top_level.txt
v440-1.1.1.dist-info/RECORD
