Metadata-Version: 2.1
Name: v440
Version: 1.1.1
Summary: mutable version objects in accordance with PEP440
Author-email: Johannes <johannes-programming@mailfence.com>
License: The MIT License (MIT)
Project-URL: Documentation, https://pypi.org/project/v440
Project-URL: Download, https://pypi.org/project/v440/#files
Project-URL: Source, https://github.com/johannes-programming/v440
Classifier: Development Status :: 5 - Production/Stable
Classifier: Intended Audience :: Developers
Classifier: License :: OSI Approved :: MIT License
Classifier: Programming Language :: Python
Classifier: Programming Language :: Python :: 3
Classifier: Programming Language :: Python :: 3 :: Only
Requires-Python: >=3.11
License-File: LICENSE.txt
Requires-Dist: datahold >=1.0
Requires-Dist: keyalias >=1.0
Requires-Dist: packaging >=23.2
Requires-Dist: scaevola >=1.0.7
